mclass/__init__.py
mclass-1.3.4.dist-info/LICENSE
mclass-1.3.4.dist-info/METADATA
mclass-1.3.4.dist-info/WHEEL
mclass-1.3.4.dist-info/top_level.txt
mclass-1.3.4.dist-info/RECORD
