Metadata-Version: 2.1
Name: mclass
Version: 1.3.4
Summary: converts python dictoinary to class object
Author: Moses Dastmard
License-File: LICENSE
